roborock/__init__.py
roborock/broadcast_protocol.py
roborock/callbacks.py
roborock/cli.py
roborock/const.py
roborock/device_features.py
roborock/diagnostics.py
roborock/exceptions.py
roborock/protocol.py
roborock/py.typed
roborock/roborock_message.py
roborock/roborock_typing.py
roborock/util.py
roborock/web_api.py
roborock/data/__init__.py
roborock/data/code_mappings.py
roborock/data/containers.py
roborock/data/b01_q10/__init__.py
roborock/data/b01_q10/b01_q10_code_mappings.py
roborock/data/b01_q10/b01_q10_containers.py
roborock/data/b01_q7/__init__.py
roborock/data/b01_q7/b01_q7_code_mappings.py
roborock/data/b01_q7/b01_q7_containers.py
roborock/data/dyad/__init__.py
roborock/data/dyad/dyad_code_mappings.py
roborock/data/dyad/dyad_containers.py
roborock/data/v1/__init__.py
roborock/data/v1/v1_clean_modes.py
roborock/data/v1/v1_code_mappings.py
roborock/data/v1/v1_containers.py
roborock/data/zeo/__init__.py
roborock/data/zeo/zeo_code_mappings.py
roborock/data/zeo/zeo_containers.py
roborock/devices/README.md
roborock/devices/__init__.py
roborock/devices/cache.py
roborock/devices/device.py
roborock/devices/device_manager.py
roborock/devices/file_cache.py
roborock/devices/rpc/__init__.py
roborock/devices/rpc/a01_channel.py
roborock/devices/rpc/b01_q10_channel.py
roborock/devices/rpc/b01_q7_channel.py
roborock/devices/rpc/v1_channel.py
roborock/devices/traits/__init__.py
roborock/devices/traits/traits_mixin.py
roborock/devices/traits/a01/__init__.py
roborock/devices/traits/b01/__init__.py
roborock/devices/traits/b01/q10/__init__.py
roborock/devices/traits/b01/q10/command.py
roborock/devices/traits/b01/q10/vacuum.py
roborock/devices/traits/b01/q7/__init__.py
roborock/devices/traits/v1/__init__.py
roborock/devices/traits/v1/child_lock.py
roborock/devices/traits/v1/clean_summary.py
roborock/devices/traits/v1/command.py
roborock/devices/traits/v1/common.py
roborock/devices/traits/v1/consumeable.py
roborock/devices/traits/v1/device_features.py
python_roborock-4.9.1.dist-info/METADATA
python_roborock-4.9.1.dist-info/WHEEL
python_roborock-4.9.1.dist-info/entry_points.txt
python_roborock-4.9.1.dist-info/licenses/LICENSE
python_roborock-4.9.1.dist-info/RECORD
