Metadata-Version: 2.4
Name: python-roborock
Version: 4.9.1
Summary: A package to control Roborock vacuums.
Project-URL: Repository, https://github.com/humbertogontijo/python-roborock
Project-URL: Documentation, https://python-roborock.readthedocs.io/
Author: Lash-L, allenporter
Author-email: humbertogontijo <humbertogontijo@users.noreply.github.com>
License-Expression: GPL-3.0-only
License-File: LICENSE
Keywords: homeassistant,roborock,vacuum
Classifier: Development Status :: 5 - Production/Stable
Classifier: Intended Audience :: Developers
Classifier: Natural Language :: English
Classifier: Operating System :: OS Independent
Classifier: Topic :: Software Development :: Libraries
Requires-Python: <4,>=3.11
Requires-Dist: aiohttp<4,>=3.8.2
Requires-Dist: aiomqtt<3,>=2.5.0
Requires-Dist: click-shell~=2.1
Requires-Dist: click>=8
Requires-Dist: construct<3,>=2.10.57
Requires-Dist: paho-mqtt<3.0.0,>=1.6.1
Requires-Dist: pycryptodomex~=3.18; sys_platform == 'darwin'
Requires-Dist: pycryptodome~=3.18
Requires-Dist: pyrate-limiter<4,>=3.7.0
Requires-Dist: vacuum-map-parser-roborock
